{
  "version": 3,
  "middleware": {
    "/": {
      "files": [
        "server/edge/chunks/_9315be0c._.js",
        "server/edge/chunks/[root of the server]__20c9a702._.js",
        "server/edge/chunks/edge-wrapper_889269fb.js"
      ],
      "name": "middleware",
      "page": "/",
      "matchers": [
        {
          "regexp": "^(?:\\/(_next\\/data\\/[^/]{1,}))?(?:\\/((?!_next|[^?]*\\.(?:html?|css|js(?!on)|jpe?g|webp|png|gif|svg|ttf|woff2?|ico|csv|docx?|xlsx?|zip|webmanifest)).*))(\\\\.json)?[\\/#\\?]?$",
          "originalSource": "/((?!_next|[^?]*\\.(?:html?|css|js(?!on)|jpe?g|webp|png|gif|svg|ttf|woff2?|ico|csv|docx?|xlsx?|zip|webmanifest)).*)"
        },
        {
          "regexp": "^(?:\\/(_next\\/data\\/[^/]{1,}))?(?:\\/(api|trpc))(.*)(\\\\.json)?[\\/#\\?]?$",
          "originalSource": "/(api|trpc)(.*)"
        }
      ],
      "wasm": [],
      "assets": [],
      "env": {
        "__NEXT_BUILD_ID": "development",
        "NEXT_SERVER_ACTIONS_ENCRYPTION_KEY": "L67VXIetUw7uUdrUen+ym37jOEkcDHSq1t7YjNmHzvg=",
        "__NEXT_PREVIEW_MODE_ID": "3504152daa1df8233de674f31f03cfc4",
        "__NEXT_PREVIEW_MODE_ENCRYPTION_KEY": "93d4b27a88a44af9eebdb930eca1e2751a05836d05540c31a786db24c3fbbd79",
        "__NEXT_PREVIEW_MODE_SIGNING_KEY": "279ed5301ff2d22a31fc3cdd129d94a9ec81f8ac1304a8229510a98154a3751f"
      }
    }
  },
  "sortedMiddleware": [
    "/"
  ],
  "functions": {}
}